r_nida/__init__.py
r_nida/location_files_code/11.csv
r_nida/location_files_code/21.csv
r_nida/location_files_code/23.csv
r_nida/location_files_code/25.csv
r_nida/location_files_code/27.csv
r_nida/location_files_code/30.csv
r_nida/location_files_code/31.csv
r_nida/location_files_code/33.csv
r_nida/location_files_code/35.csv
r_nida/location_files_code/37.csv
r_nida/location_files_code/39.csv
r_nida/location_files_code/41.csv
r_nida/location_files_code/43.csv
r_nida/location_files_code/45.csv
r_nida/location_files_code/47.csv
r_nida/location_files_code/50.csv
r_nida/location_files_code/51.csv
r_nida/location_files_code/53.csv
r_nida/location_files_code/54.csv
r_nida/location_files_code/55.csv
r_nida/location_files_code/57.csv
r_nida/location_files_code/59.csv
r_nida/location_files_code/61.csv
r_nida/location_files_code/63.csv
r_nida/location_files_code/65.csv
r_nida/location_files_code/67.csv
r_nida-0.1.0.dist-info/METADATA
r_nida-0.1.0.dist-info/WHEEL
r_nida-0.1.0.dist-info/top_level.txt
r_nida-0.1.0.dist-info/RECORD
