Metadata-Version: 2.4
Name: r_nida
Version: 0.1.0
Summary: A package for reverse engineering with NIDA
Home-page: https://github.com/Henryle-hd/r_nida
Author: Henrylee
Author-email: Henrylee <henrydionizi@gmail.com>
Project-URL: Homepage, https://github.com/Henryle-hd/reverse_nida
Project-URL: Bug Reports, https://github.com/Henryle-hd/reverse_nida/issues
Project-URL: Source, https://github.com/Henryle-hd/reverse_nida
Classifier: Development Status :: 3 - Alpha
Classifier: Intended Audience :: Developers
Classifier: License :: OSI Approved :: MIT License
Classifier: Programming Language :: Python :: 3
Requires-Python: >=3.6
Dynamic: author
Dynamic: home-page
Dynamic: requires-python
